{
  "id": "cc.0.D-delete-absorbed-skills-2026-04-29.20260429.174622093449",
  "emitter": "cc.0",
  "namespace": [
    "D-delete-absorbed-skills-2026-04-29"
  ],
  "category": "decisions",
  "kind": "decision",
  "emitted_at": "2026-04-29T17:46:22.093449",
  "links": {
    "decisions": [],
    "tickets": [],
    "commits": [],
    "whys": []
  },
  "body": {
    "decision_id": "D-delete-absorbed-skills-2026-04-29",
    "title": "D-delete-absorbed-skills-2026-04-29",
    "status": "historical",
    "original_status": "unknown",
    "date": "2026-04-29",
    "spawned_tickets": [],
    "provenance": "Absorbed from TheIgors.archive/lab/design_docs/decisions 2026-06-28 (D-all-generations-consolidation-2026-06-28); historical lineage record.",
    "text": "# Decision rollup — D-delete-absorbed-skills-2026-04-29\n\n**Closed at:** 2026-04-29T23:50:13.297745+00:00\n**Ticket count:** 1 (all closed)\n\n### Shipped via\n- T-delete-absorbed-skills (S) — Delete /review and /validate-files skills, update all callers  `done` — Deleted both skill dirs, updated 8 callers, committed.\n\n_Generated by cc_queue.py _decision_rollup. File-stub until T-decisions-into-palace-subtree moves rollups into the memory palace._\n\n## Provenance\nAbsorbed from the TheIgors.archive lineage 2026-06-28 (D-all-generations-consolidation-2026-06-28). Historical record; original status: unknown."
  }
}
